
{
	"textures": {
		"mainchar": { "path": "persotex.png" },
		"monster1": { "path": "monstertex.png" }
	},

	"spritesheets": {
		"persosheet": {
			"texture": "mainchar",
			"size": [ 5, 4 ]
		},
		"monster1sheet": {
			"texture": "monster1",
			"size": [ 3, 2 ]
		}
	},

	"animations": {
		"mainchar_walkleft": {
			"spritesheet": "persosheet",
			"frame_sequence": [ [3,4], [4,2], [2,3], [3,3] ],
			"frame_duration": [ 0.5, 0.2, 1, 0.2 ]
		},
		"mainchar_walkright": {
			"spritesheet": "persosheet",
			"frame_sequence": [ [1,2], [3,4], [2,1], [4,3] ],
			"frame_duration": [ 1, 2, 3, 4 ]
		}
	}

}


